Modulos/divisor.v
module divisor( input [2:0] DV,     //Entrada que recibirá el valor de DV (Dividendo)
				input [2:0] DR,             //Entrada que recibirá el valor de DR (Divisor)
				input start,                //Señal de control xd
				input clk,                  //Señal de reloj para sincronizar
				output [1:0] testN,         //Señales de depuración, comentar para implementar
				output testZ,               //
				output testDone,            //
				output [2:0] testA,
				output [5:0] testDV,        //
				output testdv0,             //Comentar hasta acá
				output [3:0] resultado      //Registro que entrega el resultado de la división
    );

// Señales de control
reg init;           //Es equivalente a rst en el multiplicador (Sirve para inicializar registros en sus valores default)
reg sh; 	     	    //Para habilitar el shift
reg lda;            //Para cargar A, es decir, por default A=0, pero cuando este bit vale 1, A=DVshift[5:3] (Los 3 MSB)
reg done;           //Para indicar que la división ha finalizado
reg dec;            //Habilita el decremento en 1 del contador N
reg dv0;            //Determinado por la comparación A < DR (Ver diagrama de flujo)

// Registros
reg [1:0] N;           //Contador que debe empezar en el número de bits del dividendo
reg [5:0] DVshift; 	   //Dividendo (6 bits porque se va desplazando a izq, y no se debe perder la info)
reg [2:0] A;           //Para almacenar los 3MSB de DVshift y poder almacenar la resta
reg [2:0] B; 		   //Divisor
reg [2:0] division;    //Almacena el resultado de la división
reg [2:0] status =0;   //Almacena el estado actual de la MEF (0 a 4) (5 en total)
wire z; 			   //Para poder leer la salida del comparador y saber cuando A=0 de nuevo.


// bloque comparador
assign z=(N==0)?1:0;          //Si N==0, el comparador se mantiene en 1, pero cuando eso no se cumpla, valdrá 0

assign resultado = division;

//Asignaciones de los cables para hacer depuración en simulación (Comentar estos assign, así como los outputs indicados para implementar)
assign testN = N;
assign testZ = z;
assign testDV = DVshift;
assign testdv0 = dv0;
assign testDone = done;
assign testA = A;

// bloque para las funciones de los estados 0 y 1
always @(posedge clk) begin

	if (init) begin
		DVshift <= {3'b000,DV}; //Devuelve A a su posición original (En los últimos 3 LSB), es decir, reinicia el desplazamiento
		B <= DR; //Complementa a 2 el divisor
		N <= 3;
		A <= 0;
	end	else begin
		if (sh && dec) begin
			if (dv0) begin
				A <= (A << 1) + DVshift[N-1];
				DVshift <= (DVshift << 1) + DVshift[N-1]; //Como dv0=1 solo despues de hacer desplazado DVshift y A, podemos sumar 1 a DVshift para agregar temporalmente ese 1 al resultado
			end else begin
				A <= A << 1;
				DVshift <= DVshift << 1;
			end
		N <= N - 1;
		end
	end

end

// bloque para las funciones del bloque add (La parte de evaluar dv0 se hace en el bloque anterior)
always @(posedge clk) begin

	if (lda && dv0) begin
		A <= DVshift [5:3]; //Si dv0=1 es porque A>=DR y por lo tanto se debe comenzar a almacenar la resta y a desplazarla para acabar la división, entonces, lda=1 (Load A from DVshift)
		A <= A + (~B + 1); //Resta A y B (Sumando A con el C2 de B)
	end

end
// bloque que guarda pasa el resultado a la salida
always @ ( posedge clk ) begin
	if (done) division <= {1'b0,DVshift[2:0]}; //Saca 4 bits por uniformidad de las salidas de las operaciones en la ALU
end

// FSM
parameter START =0,  SHIFT_DEC =1,  CHECK =2, ADD =3, END1 =4;

always @(posedge clk) begin
	case (status)
	START: begin                    //Inicia el estado 0
		sh=0;                         //Primero configura los valores de las señales de control del siguiente estado para que al entrar a este todo funcione OK
		lda=0;
		dec=0;
		if (start) begin
			status=SHIFT_DEC;              //Una vez se le da la orden de comenzar, pasa al estado 1
			init=1;
			done=0;
			dv0=0;
		end
		end

		SHIFT_DEC: begin
			done=0;                   //Define los valores para las señales de control tal y como se hizo en anteriores estados
			init=0;
			sh=1;
			lda=0;
			dv0=dv0;
			dec=1;
			status=CHECK;
			end

	CHECK: begin                   //Inicio del estado 2
		done=0;                      //Define los valores para las señales de control tal cual quedó en el diagrama de estados
		init=0;
		lda=0;
		sh=0;
		dec=0;
		dv0=0;
		if (z==1)                //Según lo que indique el comparador al final de definir los valores, se procederá a repetir el estado 1, o seguir al 4
			status=END1;
		else if (DVshift[5:3] < (~B+1))   //Si A < DR, el MSB de la resta será cero, acá no hay que hacer más que mandarlo a hacer shift otra vez. Pero si esa condición no se cunple, entonces se carga el registro A con los 3MSB de DVshift y se almacena de forma recursiva ese valor - DR (Ahora A almacenará el resultado de la resta y se puede desplazar)
			status=SHIFT_DEC;
		else begin
			status=ADD;
		end
	end

	ADD: begin                    //Inicio estado 3
			done=0;                   //Define los valores para las señales de control tal y como se hizo en anteriores estados
			init=0;
			sh=0;
			lda=1;
			dv0=1;
			dec=0;
			if (z==1)
				status=END1;
			else
				status=SHIFT_DEC;
		end

	END1: begin
			done=1;                   //Define los valores para las señales de control tal y como se hizo en anteriores estados
			init=0;
			sh=0;
			lda=0;
			dv0=0;
			dec=0;
			//status=START;
	end
	 default:
		status =START;
	endcase
end
endmodule

TestBench/divisor_tb.v
`timescale 1ns / 1ps
module divisor_tb;
// Inputs
  reg [2:0] DV;
  reg [2:0] DR;
  reg start;
  reg clk;

// Outputs
  wire [3:0] resultado;
// Señales para hacer depuración en la simulación, comentar para implementar
  wire [1:0] testN;
  wire testZ;
  wire testDone;
  wire [5:0] testDV;
  wire [2:0] testA;
  wire testdv0;


// Instantiate the unit under test (UUT)
divisor uut(
  .DV(DV),
  .DR(DR),
  .start(start),
  .clk(clk),
  .testN(testN),        //Comentar desde acá
  .testZ(testZ),        //
  .testDone(testDone),  //
  .testDV(testDV),      //
  .testdv0(testdv0),    //Hasta acá
  .testA(testA),
  .resultado(resultado)
);

initial begin
  // Initialize Inputs
  clk = 0;
  DV = 5;
  DR = 1;
  start = 0;

  #10 start = 1;
  
  
  //#10 start = 0;


end

always #1 clk = ~clk;

initial begin
  $dumpfile("divisor.vcd");
  $dumpvars(0,divisor_tb);
  #(40) $finish;
end

endmodule

pruebaDiv/pruebaDiv.sim/sim_1/behav/xsim/divisor.vcd
$date
   Wed Apr 27 08:35:23 2022
$end
$version
  2019.1
$end
$timescale
  1ps
$end
$scope module divisor_tb $end
$var reg 3 ! DV [2:0] $end
$var reg 3 " DR [2:0] $end
$var reg 1 # start $end
$var reg 1 $ clk $end
$var wire 4 % resultado [3:0] $end
$var wire 2 & testN [1:0] $end
$var wire 1 ' testZ $end
$var wire 1 ( testDone $end
$var wire 6 ) testDV [5:0] $end
$var wire 3 * testA [2:0] $end
$var wire 1 + testdv0 $end
$scope module uut $end
$var wire 3 , DV [2:0] $end
$var wire 3 - DR [2:0] $end
$var wire 1 . start $end
$var wire 1 / clk $end
$var wire 2 & testN [1:0] $end
$var wire 1 ' testZ $end
$var wire 1 ( testDone $end
$var wire 3 * testA [2:0] $end
$var wire 6 ) testDV [5:0] $end
$var wire 1 + testdv0 $end
$var wire 4 % resultado [3:0] $end
$var reg 1 0 init $end
$var reg 1 1 sh $end
$var reg 1 2 lda $end
$var reg 1 3 done $end
$var reg 1 4 dec $end
$var reg 1 5 dv0 $end
$var reg 2 6 N [1:0] $end
$var reg 6 7 DVshift [5:0] $end
$var reg 3 8 A [2:0] $end
$var reg 3 9 B [2:0] $end
$var reg 3 : division [2:0] $end
$var reg 3 ; status [2:0] $end
$var wire 1 < z $end
$var parameter 32 = START [31:0] $end
$var parameter 32 > SHIFT_DEC [31:0] $end
$var parameter 32 ? CHECK [31:0] $end
$var parameter 32 @ ADD [31:0] $end
$var parameter 32 A END1 [31:0] $end
$upscope $end
$upscope $end
$enddefinitions $end
#0
$dumpvars
b101 !
b1 "
0#
0$
b0xxx %
bx &
x'
x(
bx )
bx *
x+
b101 ,
b1 -
0.
0/
x0
x1
x2
x3
x4
x5
bx 6
bx 7
bx 8
bx 9
bx :
b0 ;
x<
b0 =
b1 >
b10 ?
b11 @
b100 A
$end
#1000
1$
1/
01
02
04
#2000
0$
0/
#3000
1$
1/
#4000
0$
0/
#5000
1$
1/
#6000
0$
0/
#7000
1$
1/
#8000
0$
0/
#9000
1$
1/
#10000
1#
0$
1.
0/
#11000
1$
0(
0+
1/
10
03
05
b1 ;
#12000
0$
0/
#13000
1$
b11 &
0'
b101 )
b0 *
1/
00
11
14
b11 6
b101 7
b0 8
b1 9
b10 ;
0<
#14000
0$
0/
#15000
1$
b10 &
b1010 )
1/
01
04
b10 6
b1010 7
b1 ;
0<
#16000
0$
0/
#17000
1$
1/
11
14
b10 ;
#18000
0$
0/
#19000
1$
b1 &
b10100 )
1/
01
04
b1 6
b10100 7
b1 ;
0<
#20000
0$
0/
#21000
1$
1/
11
14
b10 ;
#22000
0$
0/
#23000
1$
b0 &
1'
b101000 )
1/
01
04
b0 6
b101000 7
b1 ;
1<
#24000
0$
0/
#25000
1$
1/
11
14
b10 ;
#26000
0$
0/
#27000
1$
b11 &
0'
b10000 )
1/
01
04
b11 6
b10000 7
b100 ;
0<
#28000
0$
0/
#29000
1$
1(
1/
13
#30000
0$
0/
#31000
1$
b0 %
1/
b0 :
