Modulos/sh_l.v
`timescale 1ns / 1ps
module sh_l(
  input [2:0] portA,     //Pines para ingresar el operando (Se me ocurre que funcione el A para sll y el B para srl para no enredarse tanto con un pin que multiplexe A o B a la salida)
  input init_sh_l,       //Pin para habilitar o no este módulo (Asignar a pulsador para que refresque y no se quede en 1)
  input clk,             //Pin para sincronizar con el reloj
  input rst,             //Pin para volver al dato sin corrimientos
  output [3:0] sal_sh_l  //Pines para extraer lo que retorna este módulo y usarlo en el top-module
);

reg [3:0] A; //Registro que almacenará el número desplazado
assign sal_sh_l = A;

always @ (posedge clk) begin
  if (rst) A = {1'b0,portA}; //Devuelve A a su posición original (En los últimos 3 LSB), es decir, reinicia el desplazamiento
  else if (init_sh_l) A <= A << 1; //Desplaza A a la izquierda
end

endmodule

SimulacionIcaru/sh_l_tb.v
`timescale 1ns / 1ps
//`include "sh_l.v"
module sh_l_tb;
// Inputs
reg [2:0] portA;
reg init_sh_l;
reg clk;
reg rst;

// Outputs
wire [3:0] sal_sh_l;

// Instantiate the Unit Under Test (UUT)
sh_l uut (
  .portA(portA),
  .init_sh_l(init_sh_l),
  .clk(clk),
  .rst(rst),
  .sal_sh_l(sal_sh_l)
);


initial begin
  // Initialize Inputs
  init_sh_l = 0;
  clk = 0;
  rst = 1;
  portA = 5;

  // Wait 5 ns for global reset to finish
  #5 rst = 0;
  // Add stimulus here

  #2  init_sh_l = 1;
  #15 rst = 1;
  #2  rst = 0;
  #4  init_sh_l = 0;

end

always #1 clk = ~clk;
initial begin
     $dumpfile("sh_l.vcd");
     $dumpvars(0,sh_l_tb);
     #(40) $finish;
   end

endmodule

shift_l/shift_l.sim/sim_1/behav/xsim/sh_l.vcd
$date
   Mon Apr 25 11:54:45 2022
$end
$version
  2019.1
$end
$timescale
  1ps
$end
$scope module sh_l_tb $end
$var reg 3 ! portA [2:0] $end
$var reg 1 " init_sh_l $end
$var reg 1 # clk $end
$var reg 1 $ rst $end
$var wire 4 % sal_sh_l [3:0] $end
$scope module uut $end
$var wire 3 & portA [2:0] $end
$var wire 1 ' init_sh_l $end
$var wire 1 ( clk $end
$var wire 1 ) rst $end
$var wire 4 % sal_sh_l [3:0] $end
$var reg 4 * A [3:0] $end
$upscope $end
$upscope $end
$enddefinitions $end
#0
$dumpvars
b101 !
0"
0#
1$
bx %
b101 &
0'
0(
1)
bx *
$end
#1000
1#
b101 %
1(
b101 *
#2000
0#
0(
#3000
1#
1(
b101 *
#4000
0#
0(
#5000
1#
0$
1(
0)
#6000
0#
0(
#7000
1"
1#
b1010 %
1'
1(
b1010 *
#8000
0#
0(
#9000
1#
b100 %
1(
b100 *
#10000
0#
0(
#11000
1#
b1000 %
1(
b1000 *
#12000
0#
0(
#13000
1#
b0 %
1(
b0 *
#14000
0#
0(
#15000
1#
1(
b0 *
#16000
0#
0(
#17000
1#
1(
b0 *
#18000
0#
0(
#19000
1#
1(
b0 *
#20000
0#
0(
#21000
1#
1(
b0 *
#22000
0#
1$
0(
1)
#23000
1#
b101 %
1(
b101 *
#24000
0#
0$
0(
0)
#25000
1#
b1010 %
1(
b1010 *
#26000
0#
0(
#27000
1#
b100 %
1(
b100 *
#28000
0"
0#
0'
0(
