Modulos/divisor.v
`timescale 1ns / 1ps
module divisor
(
input [2:0] A,               //Diviendo
input [2:0] B,               //Divisor
input clk,
input init,
output reg [2:0] cociente   //Cociente
//output reg [2:0] residuo    //Residuo
);

reg[2:0] ina;
reg[2:0] inb;
reg[5:0] temp_a;
reg[5:0] temp_b;

integer i;

always @(posedge clk)    //Carga los datos a utilizar para trabajar una vez si alguna de las entradas var√≠an
begin
    if(init) begin
    ina <= A;
    inb <= B;
    /*end
end

always @(ina || inb) //Posible problema, como no es sÌncrono con reloj no le envÌa el cociente a tiempo a la ALU y esta muestra ?000 en la salida de depuraciÛn "visualizar"
begin*/
    temp_a = {3'h0,ina};
    temp_b = {inb,3'h0};
    for(i = 0;i < 3;i = i + 1)
        begin
            temp_a = temp_a << 1;
            if(temp_a[5:3] >= inb)
                temp_a = temp_a - temp_b + 1'b1;
            else
				temp_a = temp_a;
        end

    cociente <= temp_a[2:0];
    //residuo <= temp_a[5:3];
    end
end

endmodule

TestBench/divisor_tb.v
`timescale 1ns / 1ps
module divisor_tb;
// Inputs
reg [2:0] A;
reg [2:0] B;
reg clk;
reg init;
// Outputs
wire [2:0] cociente;
//wire [2:0] residuo;

initial
begin
// Initialize inputs
    clk = 0;

	#10 init = 1;
	A = 7;
	B = 2;

	#100;
	A = 1;
	B = 3;

	#100;
	A = 4;
	B = 2;

	#50 init = 0; //Para simular que se cambió de opcode y debería dejar de dividir
	#50	A = 6;
	B = 3;

	#100;
	A = 2;
	B = 7;

  end
// Instantiate the unit under test (UUT)
divisor uut
(
.A (A),
.B (B),
.clk(clk),
.init(init),
.cociente (cociente)
//.residuo (residuo)
);

always #1 clk = ~clk;
initial begin
    //$fsdbDumpvars();
    $dumpvars();
    #1000 $finish;
end

endmodule

DivisorFuncional/DivisorFuncional.sim/sim_1/behav/xsim/dump.vcd
$date
   Mon May  9 18:43:34 2022
$end
$version
  2019.1
$end
$timescale
  1ps
$end
$scope module divisor_tb $end
$var reg 3 ! A [2:0] $end
$var reg 3 " B [2:0] $end
$var reg 1 # clk $end
$var reg 1 $ init $end
$var wire 3 % cociente [2:0] $end
$scope module uut $end
$var wire 3 & A [2:0] $end
$var wire 3 ' B [2:0] $end
$var wire 1 ( clk $end
$var wire 1 ) init $end
$var reg 3 * cociente [2:0] $end
$var reg 3 + ina [2:0] $end
$var reg 3 , inb [2:0] $end
$var reg 6 - temp_a [5:0] $end
$var reg 6 . temp_b [5:0] $end
$var integer 32 / i $end
$upscope $end
$upscope $end
$enddefinitions $end
#0
$dumpvars
bx !
bx "
0#
x$
bx %
bx &
bx '
0(
x)
bx *
bx +
bx ,
bx -
bx .
bx /
$end
#1000
1#
1(
#2000
0#
0(
#3000
1#
1(
#4000
0#
0(
#5000
1#
1(
#6000
0#
0(
#7000
1#
1(
#8000
0#
0(
#9000
1#
1(
#10000
b111 !
b10 "
0#
1$
b111 &
b10 '
0(
1)
#11000
1#
b0 %
1(
b0 *
b111 +
b10 ,
bx000 -
bx000 .
b11 /
#12000
0#
0(
#13000
1#
b11 %
1(
b11 *
b111 +
b10 ,
b1011 -
b10000 .
b11 /
#14000
0#
0(
#15000
1#
1(
b11 *
b111 +
b10 ,
b1011 -
b10000 .
b11 /
#16000
0#
0(
#17000
1#
1(
b11 *
b111 +
b10 ,
b1011 -
b10000 .
b11 /
#18000
0#
0(
#19000
1#
1(
b11 *
b111 +
b10 ,
b1011 -
b10000 .
b11 /
#20000
0#
0(
#21000
1#
1(
b11 *
b111 +
b10 ,
b1011 -
b10000 .
b11 /
#22000
0#
0(
#23000
1#
1(
b11 *
b111 +
b10 ,
b1011 -
b10000 .
b11 /
#24000
0#
0(
#25000
1#
1(
b11 *
b111 +
b10 ,
b1011 -
b10000 .
b11 /
#26000
0#
0(
#27000
1#
1(
b11 *
b111 +
b10 ,
b1011 -
b10000 .
b11 /
#28000
0#
0(
#29000
1#
1(
b11 *
b111 +
b10 ,
b1011 -
b10000 .
b11 /
#30000
0#
0(
#31000
1#
1(
b11 *
b111 +
b10 ,
b1011 -
b10000 .
b11 /
#32000
0#
0(
#33000
1#
1(
b11 *
b111 +
b10 ,
b1011 -
b10000 .
b11 /
#34000
0#
0(
#35000
1#
1(
b11 *
b111 +
b10 ,
b1011 -
b10000 .
b11 /
#36000
0#
0(
#37000
1#
1(
b11 *
b111 +
b10 ,
b1011 -
b10000 .
b11 /
#38000
0#
0(
#39000
1#
1(
b11 *
b111 +
b10 ,
b1011 -
b10000 .
b11 /
#40000
0#
0(
#41000
1#
1(
b11 *
b111 +
b10 ,
b1011 -
b10000 .
b11 /
#42000
0#
0(
#43000
1#
1(
b11 *
b111 +
b10 ,
b1011 -
b10000 .
b11 /
#44000
0#
0(
#45000
1#
1(
b11 *
b111 +
b10 ,
b1011 -
b10000 .
b11 /
#46000
0#
0(
#47000
1#
1(
b11 *
b111 +
b10 ,
b1011 -
b10000 .
b11 /
#48000
0#
0(
#49000
1#
1(
b11 *
b111 +
b10 ,
b1011 -
b10000 .
b11 /
#50000
0#
0(
#51000
1#
1(
b11 *
b111 +
b10 ,
b1011 -
b10000 .
b11 /
#52000
0#
0(
#53000
1#
1(
b11 *
b111 +
b10 ,
b1011 -
b10000 .
b11 /
#54000
0#
0(
#55000
1#
1(
b11 *
b111 +
b10 ,
b1011 -
b10000 .
b11 /
#56000
0#
0(
#57000
1#
1(
b11 *
b111 +
b10 ,
b1011 -
b10000 .
b11 /
#58000
0#
0(
#59000
1#
1(
b11 *
b111 +
b10 ,
b1011 -
b10000 .
b11 /
#60000
0#
0(
#61000
1#
1(
b11 *
b111 +
b10 ,
b1011 -
b10000 .
b11 /
#62000
0#
0(
#63000
1#
1(
b11 *
b111 +
b10 ,
b1011 -
b10000 .
b11 /
#64000
0#
0(
#65000
1#
1(
b11 *
b111 +
b10 ,
b1011 -
b10000 .
b11 /
#66000
0#
0(
#67000
1#
1(
b11 *
b111 +
b10 ,
b1011 -
b10000 .
b11 /
#68000
0#
0(
#69000
1#
1(
b11 *
b111 +
b10 ,
b1011 -
b10000 .
b11 /
#70000
0#
0(
#71000
1#
1(
b11 *
b111 +
b10 ,
b1011 -
b10000 .
b11 /
#72000
0#
0(
#73000
1#
1(
b11 *
b111 +
b10 ,
b1011 -
b10000 .
b11 /
#74000
0#
0(
#75000
1#
1(
b11 *
b111 +
b10 ,
b1011 -
b10000 .
b11 /
#76000
0#
0(
#77000
1#
1(
b11 *
b111 +
b10 ,
b1011 -
b10000 .
b11 /
#78000
0#
0(
#79000
1#
1(
b11 *
b111 +
b10 ,
b1011 -
b10000 .
b11 /
#80000
0#
0(
#81000
1#
1(
b11 *
b111 +
b10 ,
b1011 -
b10000 .
b11 /
#82000
0#
0(
#83000
1#
1(
b11 *
b111 +
b10 ,
b1011 -
b10000 .
b11 /
#84000
0#
0(
#85000
1#
1(
b11 *
b111 +
b10 ,
b1011 -
b10000 .
b11 /
#86000
0#
0(
#87000
1#
1(
b11 *
b111 +
b10 ,
b1011 -
b10000 .
b11 /
#88000
0#
0(
#89000
1#
1(
b11 *
b111 +
b10 ,
b1011 -
b10000 .
b11 /
#90000
0#
0(
#91000
1#
1(
b11 *
b111 +
b10 ,
b1011 -
b10000 .
b11 /
#92000
0#
0(
#93000
1#
1(
b11 *
b111 +
b10 ,
b1011 -
b10000 .
b11 /
#94000
0#
0(
#95000
1#
1(
b11 *
b111 +
b10 ,
b1011 -
b10000 .
b11 /
#96000
0#
0(
#97000
1#
1(
b11 *
b111 +
b10 ,
b1011 -
b10000 .
b11 /
#98000
0#
0(
#99000
1#
1(
b11 *
b111 +
b10 ,
b1011 -
b10000 .
b11 /
#100000
0#
0(
#101000
1#
1(
b11 *
b111 +
b10 ,
b1011 -
b10000 .
b11 /
#102000
0#
0(
#103000
1#
1(
b11 *
b111 +
b10 ,
b1011 -
b10000 .
b11 /
#104000
0#
0(
#105000
1#
1(
b11 *
b111 +
b10 ,
b1011 -
b10000 .
b11 /
#106000
0#
0(
#107000
1#
1(
b11 *
b111 +
b10 ,
b1011 -
b10000 .
b11 /
#108000
0#
0(
#109000
1#
1(
b11 *
b111 +
b10 ,
b1011 -
b10000 .
b11 /
#110000
b1 !
b11 "
0#
b1 &
b11 '
0(
#111000
1#
1(
b11 *
b1 +
b11 ,
b1011 -
b10000 .
b11 /
#112000
0#
0(
#113000
1#
b0 %
1(
b0 *
b1 +
b11 ,
b1000 -
b11000 .
b11 /
#114000
0#
0(
#115000
1#
1(
b0 *
b1 +
b11 ,
b1000 -
b11000 .
b11 /
#116000
0#
0(
#117000
1#
1(
b0 *
b1 +
b11 ,
b1000 -
b11000 .
b11 /
#118000
0#
0(
#119000
1#
1(
b0 *
b1 +
b11 ,
b1000 -
b11000 .
b11 /
#120000
0#
0(
#121000
1#
1(
b0 *
b1 +
b11 ,
b1000 -
b11000 .
b11 /
#122000
0#
0(
#123000
1#
1(
b0 *
b1 +
b11 ,
b1000 -
b11000 .
b11 /
#124000
0#
0(
#125000
1#
1(
b0 *
b1 +
b11 ,
b1000 -
b11000 .
b11 /
#126000
0#
0(
#127000
1#
1(
b0 *
b1 +
b11 ,
b1000 -
b11000 .
b11 /
#128000
0#
0(
#129000
1#
1(
b0 *
b1 +
b11 ,
b1000 -
b11000 .
b11 /
#130000
0#
0(
#131000
1#
1(
b0 *
b1 +
b11 ,
b1000 -
b11000 .
b11 /
#132000
0#
0(
#133000
1#
1(
b0 *
b1 +
b11 ,
b1000 -
b11000 .
b11 /
#134000
0#
0(
#135000
1#
1(
b0 *
b1 +
b11 ,
b1000 -
b11000 .
b11 /
#136000
0#
0(
#137000
1#
1(
b0 *
b1 +
b11 ,
b1000 -
b11000 .
b11 /
#138000
0#
0(
#139000
1#
1(
b0 *
b1 +
b11 ,
b1000 -
b11000 .
b11 /
#140000
0#
0(
#141000
1#
1(
b0 *
b1 +
b11 ,
b1000 -
b11000 .
b11 /
#142000
0#
0(
#143000
1#
1(
b0 *
b1 +
b11 ,
b1000 -
b11000 .
b11 /
#144000
0#
0(
#145000
1#
1(
b0 *
b1 +
b11 ,
b1000 -
b11000 .
b11 /
#146000
0#
0(
#147000
1#
1(
b0 *
b1 +
b11 ,
b1000 -
b11000 .
b11 /
#148000
0#
0(
#149000
1#
1(
b0 *
b1 +
b11 ,
b1000 -
b11000 .
b11 /
#150000
0#
0(
#151000
1#
1(
b0 *
b1 +
b11 ,
b1000 -
b11000 .
b11 /
#152000
0#
0(
#153000
1#
1(
b0 *
b1 +
b11 ,
b1000 -
b11000 .
b11 /
#154000
0#
0(
#155000
1#
1(
b0 *
b1 +
b11 ,
b1000 -
b11000 .
b11 /
#156000
0#
0(
#157000
1#
1(
b0 *
b1 +
b11 ,
b1000 -
b11000 .
b11 /
#158000
0#
0(
#159000
1#
1(
b0 *
b1 +
b11 ,
b1000 -
b11000 .
b11 /
#160000
0#
0(
#161000
1#
1(
b0 *
b1 +
b11 ,
b1000 -
b11000 .
b11 /
#162000
0#
0(
#163000
1#
1(
b0 *
b1 +
b11 ,
b1000 -
b11000 .
b11 /
#164000
0#
0(
#165000
1#
1(
b0 *
b1 +
b11 ,
b1000 -
b11000 .
b11 /
#166000
0#
0(
#167000
1#
1(
b0 *
b1 +
b11 ,
b1000 -
b11000 .
b11 /
#168000
0#
0(
#169000
1#
1(
b0 *
b1 +
b11 ,
b1000 -
b11000 .
b11 /
#170000
0#
0(
#171000
1#
1(
b0 *
b1 +
b11 ,
b1000 -
b11000 .
b11 /
#172000
0#
0(
#173000
1#
1(
b0 *
b1 +
b11 ,
b1000 -
b11000 .
b11 /
#174000
0#
0(
#175000
1#
1(
b0 *
b1 +
b11 ,
b1000 -
b11000 .
b11 /
#176000
0#
0(
#177000
1#
1(
b0 *
b1 +
b11 ,
b1000 -
b11000 .
b11 /
#178000
0#
0(
#179000
1#
1(
b0 *
b1 +
b11 ,
b1000 -
b11000 .
b11 /
#180000
0#
0(
#181000
1#
1(
b0 *
b1 +
b11 ,
b1000 -
b11000 .
b11 /
#182000
0#
0(
#183000
1#
1(
b0 *
b1 +
b11 ,
b1000 -
b11000 .
b11 /
#184000
0#
0(
#185000
1#
1(
b0 *
b1 +
b11 ,
b1000 -
b11000 .
b11 /
#186000
0#
0(
#187000
1#
1(
b0 *
b1 +
b11 ,
b1000 -
b11000 .
b11 /
#188000
0#
0(
#189000
1#
1(
b0 *
b1 +
b11 ,
b1000 -
b11000 .
b11 /
#190000
0#
0(
#191000
1#
1(
b0 *
b1 +
b11 ,
b1000 -
b11000 .
b11 /
#192000
0#
0(
#193000
1#
1(
b0 *
b1 +
b11 ,
b1000 -
b11000 .
b11 /
#194000
0#
0(
#195000
1#
1(
b0 *
b1 +
b11 ,
b1000 -
b11000 .
b11 /
#196000
0#
0(
#197000
1#
1(
b0 *
b1 +
b11 ,
b1000 -
b11000 .
b11 /
#198000
0#
0(
#199000
1#
1(
b0 *
b1 +
b11 ,
b1000 -
b11000 .
b11 /
#200000
0#
0(
#201000
1#
1(
b0 *
b1 +
b11 ,
b1000 -
b11000 .
b11 /
#202000
0#
0(
#203000
1#
1(
b0 *
b1 +
b11 ,
b1000 -
b11000 .
b11 /
#204000
0#
0(
#205000
1#
1(
b0 *
b1 +
b11 ,
b1000 -
b11000 .
b11 /
#206000
0#
0(
#207000
1#
1(
b0 *
b1 +
b11 ,
b1000 -
b11000 .
b11 /
#208000
0#
0(
#209000
1#
1(
b0 *
b1 +
b11 ,
b1000 -
b11000 .
b11 /
#210000
b100 !
b10 "
0#
b100 &
b10 '
0(
#211000
1#
1(
b0 *
b100 +
b10 ,
b1000 -
b11000 .
b11 /
#212000
0#
0(
#213000
1#
b10 %
1(
b10 *
b100 +
b10 ,
b10 -
b10000 .
b11 /
#214000
0#
0(
#215000
1#
1(
b10 *
b100 +
b10 ,
b10 -
b10000 .
b11 /
#216000
0#
0(
#217000
1#
1(
b10 *
b100 +
b10 ,
b10 -
b10000 .
b11 /
#218000
0#
0(
#219000
1#
1(
b10 *
b100 +
b10 ,
b10 -
b10000 .
b11 /
#220000
0#
0(
#221000
1#
1(
b10 *
b100 +
b10 ,
b10 -
b10000 .
b11 /
#222000
0#
0(
#223000
1#
1(
b10 *
b100 +
b10 ,
b10 -
b10000 .
b11 /
#224000
0#
0(
#225000
1#
1(
b10 *
b100 +
b10 ,
b10 -
b10000 .
b11 /
#226000
0#
0(
#227000
1#
1(
b10 *
b100 +
b10 ,
b10 -
b10000 .
b11 /
#228000
0#
0(
#229000
1#
1(
b10 *
b100 +
b10 ,
b10 -
b10000 .
b11 /
#230000
0#
0(
#231000
1#
1(
b10 *
b100 +
b10 ,
b10 -
b10000 .
b11 /
#232000
0#
0(
#233000
1#
1(
b10 *
b100 +
b10 ,
b10 -
b10000 .
b11 /
#234000
0#
0(
#235000
1#
1(
b10 *
b100 +
b10 ,
b10 -
b10000 .
b11 /
#236000
0#
0(
#237000
1#
1(
b10 *
b100 +
b10 ,
b10 -
b10000 .
b11 /
#238000
0#
0(
#239000
1#
1(
b10 *
b100 +
b10 ,
b10 -
b10000 .
b11 /
#240000
0#
0(
#241000
1#
1(
b10 *
b100 +
b10 ,
b10 -
b10000 .
b11 /
#242000
0#
0(
#243000
1#
1(
b10 *
b100 +
b10 ,
b10 -
b10000 .
b11 /
#244000
0#
0(
#245000
1#
1(
b10 *
b100 +
b10 ,
b10 -
b10000 .
b11 /
#246000
0#
0(
#247000
1#
1(
b10 *
b100 +
b10 ,
b10 -
b10000 .
b11 /
#248000
0#
0(
#249000
1#
1(
b10 *
b100 +
b10 ,
b10 -
b10000 .
b11 /
#250000
0#
0(
#251000
1#
1(
b10 *
b100 +
b10 ,
b10 -
b10000 .
b11 /
#252000
0#
0(
#253000
1#
1(
b10 *
b100 +
b10 ,
b10 -
b10000 .
b11 /
#254000
0#
0(
#255000
1#
1(
b10 *
b100 +
b10 ,
b10 -
b10000 .
b11 /
#256000
0#
0(
#257000
1#
1(
b10 *
b100 +
b10 ,
b10 -
b10000 .
b11 /
#258000
0#
0(
#259000
1#
1(
b10 *
b100 +
b10 ,
b10 -
b10000 .
b11 /
#260000
0#
0$
0(
0)
